{"name":"testcase-CN10-small-2.json","id":"testcase-CN10-small-2.json","file":"testcase-CN10-small-2.json","train":[{"name":"Piano sound with -N0","id":"piano-50-N0","file":"piano-50-N0.wav","type":"P","noise":0},{"name":"Piano sound with -N0","id":"piano-30-N0","file":"piano-30-N0.wav","type":"P","noise":0},{"name":"Piano sound with -N0","id":"piano-28-N0","file":"piano-28-N0.wav","type":"P","noise":0},{"name":"Piano sound with -N0","id":"piano-34-N0","file":"piano-34-N0.wav","type":"P","noise":0},{"name":"Piano sound with -N0","id":"piano-41-N0","file":"piano-41-N0.wav","type":"P","noise":0},{"name":"Violin sound with -N0","id":"violin-47-N0","file":"violin-47-N0.wav","type":"V","noise":0},{"name":"Violin sound with -N0","id":"violin-49-N0","file":"violin-49-N0.wav","type":"V","noise":0},{"name":"Violin sound with -N0","id":"violin-11-N0","file":"violin-11-N0.wav","type":"V","noise":0},{"name":"Violin sound with -N0","id":"violin-37-N0","file":"violin-37-N0.wav","type":"V","noise":0},{"name":"Violin sound with -N0","id":"violin-18-N0","file":"violin-18-N0.wav","type":"V","noise":0},{"name":"Guitar sound with -N0","id":"guitar-27-N0","file":"guitar-27-N0.wav","type":"G","noise":0},{"name":"Guitar sound with -N0","id":"guitar-34-N0","file":"guitar-34-N0.wav","type":"G","noise":0},{"name":"Guitar sound with -N0","id":"guitar-15-N0","file":"guitar-15-N0.wav","type":"G","noise":0},{"name":"Guitar sound with -N0","id":"guitar-23-N0","file":"guitar-23-N0.wav","type":"G","noise":0},{"name":"Guitar sound with -N0","id":"guitar-2-N0","file":"guitar-2-N0.wav","type":"G","noise":0}],"test":[{"name":"Piano sound with -N0","id":"piano-38-N0","file":"piano-38-N0.wav","type":"P","noise":0},{"name":"Piano sound with -N0","id":"piano-10-N0","file":"piano-10-N0.wav","type":"P","noise":0},{"name":"Piano sound with -N0","id":"piano-16-N0","file":"piano-16-N0.wav","type":"P","noise":0},{"name":"Piano sound with -N0","id":"piano-46-N0","file":"piano-46-N0.wav","type":"P","noise":0},{"name":"Piano sound with -N0","id":"piano-31-N0","file":"piano-31-N0.wav","type":"P","noise":0},{"name":"Violin sound with -N0","id":"violin-7-N0","file":"violin-7-N0.wav","type":"V","noise":0},{"name":"Violin sound with -N0","id":"violin-1-N0","file":"violin-1-N0.wav","type":"V","noise":0},{"name":"Violin sound with -N0","id":"violin-30-N0","file":"violin-30-N0.wav","type":"V","noise":0},{"name":"Violin sound with -N0","id":"violin-40-N0","file":"violin-40-N0.wav","type":"V","noise":0},{"name":"Violin sound with -N0","id":"violin-28-N0","file":"violin-28-N0.wav","type":"V","noise":0},{"name":"Guitar sound with -N0","id":"guitar-5-N0","file":"guitar-5-N0.wav","type":"G","noise":0},{"name":"Guitar sound with -N0","id":"guitar-7-N0","file":"guitar-7-N0.wav","type":"G","noise":0},{"name":"Guitar sound with -N0","id":"guitar-25-N0","file":"guitar-25-N0.wav","type":"G","noise":0},{"name":"Guitar sound with -N0","id":"guitar-31-N0","file":"guitar-31-N0.wav","type":"G","noise":0},{"name":"Guitar sound with -N0","id":"guitar-8-N0","file":"guitar-8-N0.wav","type":"G","noise":0}]}